{
  "name": "Blastoise",
  "pokedexNumber": 9,
  "type1": "water",
  "evolution": [
    {
      "basePokemonName": "squirtle",
      "evolution1": {
        "evolutionName": "wartortle",
        "method": 16
      },
      "evolution2": {
        "evolutionName": "blastoise",
        "method": 36
      }
    }
  ],
  "otherNames": {
    "Japanese": "Kamex",
    "French": "Tortank",
    "German": "Turtok",
    "Korean": "거북왕"
  },
  "classification": "Shellfish",
  "height": 1.6,
  "weight": 85.5,
  "captureRate": 45,
  "baseStats": {
    "hp": 79,
    "attack": 83,
    "defense": 100,
    "special": 85,
    "speed": 78
  },
  "locations": {
    "red": "Evolve Wartortle",
    "blue": "Evolve Wartortle",
    "yellow": "Evolve Wartortle"
  },
  "attacks": [
    {
      "level": "baseAttack",
      "attackId": "tackle"
    },
    {
      "level": "baseAttack",
      "attackId": "tail-whip"
    },
    {
      "level": "baseAttack",
      "attackId": "bubble"
    },
    {
      "level": "baseAttack",
      "attackId": "water-gun"
    },
    {
      "level": 8,
      "attackId": "bubble"
    },
    {
      "level": 15,
      "attackId": "water-gun"
    },
    {
      "level": 24,
      "attackId": "bite"
    },
    {
      "level": 31,
      "attackId": "withdraw"
    },
    {
      "level": 42,
      "attackId": "skull-bash"
    },
    {
      "level": 52,
      "attackId": "hydro-pump"
    }
  ],
  "tms": [
    "tm01",
    "tm05",
    "tm06",
    "tm08",
    "tm09",
    "tm10",
    "tm11",
    "tm12",
    "tm13",
    "tm14",
    "tm15",
    "tm17",
    "tm18",
    "tm19",
    "tm20",
    "tm26",
    "tm27",
    "tm28",
    "tm31",
    "tm32",
    "tm33",
    "tm34",
    "tm40",
    "tm44",
    "tm50",
    "hm03",
    "hm04"
  ]
}
