{
  "name": "Electrode",
  "pokedexNumber": 101,
  "type1": "electric",
  "evolution": [
    {
      "basePokemonName": "voltorb",
      "evolution1": {
        "evolutionName": "electrode",
        "method": 30
      }
    }
  ],
  "otherNames": {
    "Japanese": "Marumine",
    "French": "Électrode",
    "German": "Lektrobal",
    "Korean": "붐볼"
  },
  "classification": "Ball",
  "height": 1.2,
  "weight": 66.6,
  "captureRate": 60,
  "baseStats": {
    "hp": 60,
    "attack": 50,
    "defense": 70,
    "special": 80,
    "speed": 140
  },
  "locations": {
    "red": "Cerulean Cave",
    "blue": "Cerulean Cave",
    "yellow": "Evolve Voltorb"
  },
  "attacks": [
    {
      "level": "baseAttack",
      "attackId": "tackle"
    },
    {
      "level": "baseAttack",
      "attackId": "screech"
    },
    {
      "level": "baseAttack",
      "attackId": "sonicboom"
    },
    {
      "level": 17,
      "attackId": "sonicboom"
    },
    {
      "level": 22,
      "attackId": "selfdestruct"
    },
    {
      "level": 29,
      "attackId": "lightscreen"
    },
    {
      "level": 40,
      "attackId": "swift"
    },
    {
      "level": 50,
      "attackId": "explosion"
    }
  ],
  "tms": [
    "tm06",
    "tm09",
    "tm15",
    "tm24",
    "tm25",
    "tm30",
    "tm31",
    "tm32",
    "tm33",
    "tm34",
    "tm36",
    "tm39",
    "tm44",
    "tm45",
    "tm47",
    "tm50",
    "hm05"
  ]
}
