{
  "name": "Pidgeotto",
  "pokedexNumber": 17,
  "type1": "normal",
  "type2": "flying",
  "evolution": [
    {
      "basePokemonName": "pidgey",
      "evolution1": {
        "evolutionName": "pidgeotto",
        "method": 18
      },
      "evolution2": {
        "evolutionName": "pidgeot",
        "method": 36
      }
    }
  ],
  "otherNames": {
    "Japanese": "Pigeon",
    "French": "Roucoups",
    "German": "Tauboga",
    "Korean": "피죤"
  },
  "classification": "Bird",
  "height": 1.1,
  "weight": 30,
  "captureRate": 120,
  "baseStats": {
    "hp": 63,
    "attack": 60,
    "defense": 55,
    "special": 50,
    "speed": 71
  },
  "locations": {
    "red": "Route 14, Route 15, Route 21",
    "blue": "Route 14, Route 15, Route 21",
    "yellow": "Route 5, Route 6, Route 7, Route 8, Route 11, Route 12, Route 13, Route 14, Route 15, Route 21, Route 24, Route 25, Viridian Forest"
  },
  "attacks": [
    {
      "level": "baseAttack",
      "attackId": "gust"
    },
    {
      "level": "baseAttack",
      "attackId": "sandattack"
    },
    {
      "level": 5,
      "attackId": "sandattack"
    },
    {
      "level": 12,
      "attackId": "quickattack"
    },
    {
      "level": 21,
      "attackId": "whirlwind"
    },
    {
      "level": 31,
      "attackId": "wingattack"
    },
    {
      "level": 40,
      "attackId": "agility"
    },
    {
      "level": 49,
      "attackId": "mirrormove"
    }
  ],
  "tms": [
    "tm02",
    "tm04",
    "tm06",
    "tm09",
    "tm10",
    "tm20",
    "tm31",
    "tm32",
    "tm33",
    "tm34",
    "tm39",
    "tm43",
    "tm44",
    "tm50",
    "hm02"
  ]
}
